MANIFEST.in
README.rst
setup.py
docs/HISTORY.txt
docs/INSTALL.txt
docs/LICENSE.GPL
docs/LICENSE.txt
ftw/__init__.py
ftw.contentmenu.egg-info/PKG-INFO
ftw.contentmenu.egg-info/SOURCES.txt
ftw.contentmenu.egg-info/dependency_links.txt
ftw.contentmenu.egg-info/entry_points.txt
ftw.contentmenu.egg-info/namespace_packages.txt
ftw.contentmenu.egg-info/not-zip-safe
ftw.contentmenu.egg-info/requires.txt
ftw.contentmenu.egg-info/top_level.txt
ftw/contentmenu/__init__.py
ftw/contentmenu/configure.zcml
ftw/contentmenu/interfaces.py
ftw/contentmenu/menu.py
ftw/contentmenu/testing.py
ftw/contentmenu/profiles/default/browserlayer.xml
ftw/contentmenu/profiles/default/metadata.xml
ftw/contentmenu/tests/__init__.py
ftw/contentmenu/tests/test_menu.py
ftw/contentmenu/upgrades/__init__.py
ftw/contentmenu/upgrades/configure.zcml
ftw/contentmenu/upgrades/profiles/to_v2001/cssregistry.xml
ftw/contentmenu/upgrades/profiles/to_v2001/metadata.xml
ftw/contentmenu/upgrades/profiles/to_v2001/viewlets.xml