Metadata-Version: 1.0
Name: ftw.contentmenu
Version: 2.2.2
Summary: Customize Plone's content menu
Home-page: https://github.com/4teamwork/ftw.contentmenu
Author: 4teamwork GmbH
Author-email: mailto:info@4teamwork.ch
License: GPL2
Keywords: ftw contentmenu plone
Platform: UNKNOWN
Classifier: Framework :: Plone
Classifier: Framework :: Plone :: 4.1
Classifier: Framework :: Plone :: 4.2
Classifier: Framework :: Plone :: 4.3
Classifier: Programming Language :: Python
Classifier: Topic :: Software Development :: Libraries :: Python Modules
